simplemosaic/__init__.py
simplemosaic/__main__.py
simplemosaic/app.py
simplemosaic/algorithms/__init__.py
simplemosaic/algorithms/gray_mosaic.py
simplemosaic/converters/__init__.py
simplemosaic/preprocessing/__init__.py
simplemosaic-0.0.1.dist-info/LICENSE.md
simplemosaic-0.0.1.dist-info/METADATA
simplemosaic-0.0.1.dist-info/WHEEL
simplemosaic-0.0.1.dist-info/top_level.txt
simplemosaic-0.0.1.dist-info/RECORD
