Metadata-Version: 2.1
Name: simplemosaic
Version: 0.0.1
Summary: A small example package
Home-page: https://github.com/szjakub/simplemosaic
Author: Jakub Szkodny
Author-email: jakubszkodny@gmail.com
License: UNKNOWN
Platform: UNKNOWN
Classifier: Development Status :: 1 - Planning
Classifier: Programming Language :: Python :: 3
Classifier: License :: OSI Approved :: MIT License
Classifier: Operating System :: OS Independent
Requires-Python: >=3.6
Requires-Dist: opencv-python (==4.1.2.30)
Requires-Dist: numpy (==1.18.0)
